轉換器.py
TP2Unicode/__init__.py
TP2Unicode/unicode.csv
TP2Unicode/轉換器.py
TP2Unicode/data/unicode.csv
Taiwanese-serif-to-Unicode/__init__.py
Taiwanese-serif-to-Unicode/轉換器.py
TP2Unicode-0.0.9.dist-info/LICENSE
TP2Unicode-0.0.9.dist-info/METADATA
TP2Unicode-0.0.9.dist-info/WHEEL
TP2Unicode-0.0.9.dist-info/top_level.txt
TP2Unicode-0.0.9.dist-info/RECORD
