Metadata-Version: 2.1
Name: TP2Unicode
Version: 0.0.9
Summary: 共Taiwanese package拍出來的羅馬字轉做其他環境mā會當顯示的編碼
Home-page: https://github.com/i3thuan5/Taiwanese-serif-to-Unicode
Author: Tân, Khèng-iông
Author-email: fernandochen799@gmail.com
License: UNKNOWN
Platform: UNKNOWN
Classifier: Programming Language :: Python :: 3
Classifier: License :: OSI Approved :: MIT License
Classifier: Operating System :: OS Independent
